soccer_cv/__init__.py
soccer_cv/compare.py
soccer_cv/config.py
soccer_cv/devices.py
soccer_cv/geometry.py
soccer_cv/io/video.py
soccer_cv/models.py
soccer_cv/pipelines/__init__.py
soccer_cv/pipelines/ball_path.py
soccer_cv/pipelines/common.py
soccer_cv/pipelines/player_heatmaps.py
soccer_cv/pipelines/possession.py
soccer_cv/pipelines/team_shape.py
soccer_cv/pipelines/tracking.py
soccer_cv/pipelines/voronoi.py
soccer_cv/utils.py
soccer_cv-0.1.5.dist-info/LICENSE
soccer_cv-0.1.5.dist-info/METADATA
soccer_cv-0.1.5.dist-info/WHEEL
soccer_cv-0.1.5.dist-info/RECORD
