Metadata-Version: 2.3
Name: soccer-cv
Version: 0.1.5
Summary: Soccer CV library
License: MIT
Author: Grant Hohol
Author-email: ghohol@wisc.edu
Requires-Python: >=3.10,<3.13
Classifier: Development Status :: 3 - Alpha
Classifier: Intended Audience :: Developers
Classifier: License :: OSI Approved :: MIT License
Classifier: Operating System :: POSIX :: Linux
Classifier: Programming Language :: Python :: 3
Classifier: Programming Language :: Python :: 3.10
Classifier: Programming Language :: Python :: 3.11
Classifier: Programming Language :: Python :: 3.12
Classifier: Topic :: Scientific/Engineering :: Image Processing
Provides-Extra: all
Provides-Extra: cpu
Provides-Extra: cuda
Provides-Extra: data
Provides-Extra: dev
Provides-Extra: mps
Requires-Dist: PyYAML (>=6.0) ; extra == "mps" or extra == "cuda" or extra == "all"
Requires-Dist: huggingface_hub (>=0.34.4,<0.35.0)
Requires-Dist: numpy (>=2,<2.3.0)
Requires-Dist: opencv-python-headless (>=4.10.0.84,<5.0.0)
Requires-Dist: pandas (>=2.3.2,<3.0.0) ; extra == "data" or extra == "all"
Requires-Dist: pyarrow (>=21.0.0,<22.0.0) ; extra == "data" or extra == "all"
Requires-Dist: pytest (>=8.4.1,<9.0.0) ; extra == "dev" or extra == "all"
Requires-Dist: roboflow (>=1.2.3,<2.0.0)
Requires-Dist: supervision (>=0.26.1,<0.27.0)
Requires-Dist: tabulate (>=0.9.0,<0.10.0)
Requires-Dist: torch (>=2.4.1,<3) ; extra == "cpu" or extra == "mps"
Requires-Dist: torchvision (>=0.19.1,<1) ; extra == "cpu" or extra == "mps"
Requires-Dist: tqdm (>=4.67.1,<5.0.0)
Requires-Dist: ultralytics (>=8.3.176,<9.0.0)
Project-URL: Homepage, https://github.com/granthohol/soccer-cv
Project-URL: Issues, https://github.com/granthohol/soccer-cv/issues
Project-URL: Source, https://github.com/granthohol/soccer-cv
